mxslc/Argument.py
mxslc/Attribute.py
mxslc/CompileError.py
mxslc/DataType.py
mxslc/Function.py
mxslc/Keyword.py
mxslc/Parameter.py
mxslc/Token.py
mxslc/TokenReader.py
mxslc/__init__.py
mxslc/compile.py
mxslc/compile_file.py
mxslc/document.py
mxslc/file_utils.py
mxslc/load_library.py
mxslc/mx_wrapper.py
mxslc/node_utils.py
mxslc/parse.py
mxslc/post_process.py
mxslc/scan.py
mxslc/state.py
mxslc/token_types.py
mxslc/utils.py
mxslc/Decompiler/DecompileError.py
mxslc/Decompiler/__init__.py
mxslc/Decompiler/decompile.py
mxslc/Expressions/BinaryExpression.py
mxslc/Expressions/ConstructorCall.py
mxslc/Expressions/Expression.py
mxslc/Expressions/FunctionCall.py
mxslc/Expressions/GroupingExpression.py
mxslc/Expressions/IdentifierExpression.py
mxslc/Expressions/IfExpression.py
mxslc/Expressions/IndexingExpression.py
mxslc/Expressions/LiteralExpression.py
mxslc/Expressions/NodeConstructor.py
mxslc/Expressions/SwitchExpression.py
mxslc/Expressions/SwizzleExpression.py
mxslc/Expressions/TernaryRelationalExpression.py
mxslc/Expressions/UnaryExpression.py
mxslc/Expressions/ValueExpression.py
mxslc/Expressions/VariableDeclarationExpression.py
mxslc/Expressions/__init__.py
mxslc/Expressions/expression_utils.py
mxslc/Interactive/InteractiveCompiler.py
mxslc/Interactive/InteractiveExpression.py
mxslc/Interactive/InteractiveNode.py
mxslc/Interactive/ShaderInterface.py
mxslc/Interactive/__init__.py
mxslc/Interactive/mx_interactive_types.py
mxslc/Preprocessor/Directive.py
mxslc/Preprocessor/Expression.py
mxslc/Preprocessor/__init__.py
mxslc/Preprocessor/macros.py
mxslc/Preprocessor/parse.py
mxslc/Preprocessor/process.py
mxslc/Statements/CompoundAssignment.py
mxslc/Statements/ExpressionStatement.py
mxslc/Statements/ForLoop.py
mxslc/Statements/FunctionDeclaration.py
mxslc/Statements/Statement.py
mxslc/Statements/VariableAssignment.py
mxslc/Statements/VariableDeclaration.py
mxslc/Statements/__init__.py
mxslc/libraries/slxlib_defs.mxsl
mxslc/libraries/1.38.10/bxdf/disney_brdf_2012.mtlx
mxslc-0.6.5.dist-info/licenses/LICENSE
mxslc-0.6.5.dist-info/METADATA
mxslc-0.6.5.dist-info/WHEEL
mxslc-0.6.5.dist-info/top_level.txt
mxslc-0.6.5.dist-info/RECORD
