Metadata-Version: 2.4
Name: mxslc
Version: 0.6.5
Summary: ShadingLanguageX open-source compiler
Author-email: Jake Thorn <jakethorn1.1@gmail.com>
License-Expression: Apache-2.0
Project-URL: Homepage, https://github.com/jakethorn/ShadingLanguageX
Project-URL: Documentation, https://github.com/jakethorn/ShadingLanguageX/blob/master/docs/LanguageSpecification.md
Project-URL: Issues, https://github.com/jakethorn/ShadingLanguageX/issues
Project-URL: Changelog, https://github.com/jakethorn/ShadingLanguageX/blob/master/CHANGELOG.md
Keywords: ShadingLanguageX,MaterialX,USD,shader,shading language
Classifier: Development Status :: 4 - Beta
Classifier: Programming Language :: Python :: 3.12
Classifier: Programming Language :: Python :: 3.13
Classifier: Operating System :: OS Independent
Requires-Python: >=3.12
License-File: LICENSE
Requires-Dist: MaterialX~=1.39.3
Requires-Dist: pytest~=8.3.5
Dynamic: license-file
